nomad_tools/__init__.py
nomad_tools/aliasedgroup.py
nomad_tools/aliasedlazygroup.py
nomad_tools/colors.py
nomad_tools/common.py
nomad_tools/common_click.py
nomad_tools/common_nomad.py
nomad_tools/entry.py
nomad_tools/entry_changed.py
nomad_tools/entry_constrainteval.py
nomad_tools/entry_cp.py
nomad_tools/entry_dockers.py
nomad_tools/entry_downloadrelease.py
nomad_tools/entry_gitlab_runner.py
nomad_tools/entry_go.py
nomad_tools/entry_info.py
nomad_tools/entry_listattributes.py
nomad_tools/entry_listnodeattributes.py
nomad_tools/entry_nodenametoid.py
nomad_tools/entry_port.py
nomad_tools/entry_task.py
nomad_tools/entry_vardir.py
nomad_tools/entry_watch.py
nomad_tools/entrypoint.py
nomad_tools/exit_on_thread_exception.py
nomad_tools/flagdebug.py
nomad_tools/forward_args_to_nomad.py
nomad_tools/mytabulate.py
nomad_tools/nomad_smart_start_job.py
nomad_tools/nomaddbjob.py
nomad_tools/nomadt_completion.sh
nomad_tools/taskexec.py
nomad_tools/transferstats.py
nomad_tools/entry_githubrunner/__init__.py
nomad_tools/entry_githubrunner/default.nomad.hcl
nomad_tools/entry_githubrunner/entry_githubrunner.py
nomad_tools/entry_githubrunner/entrypoint.sh
nomad_tools/entry_githubrunner/trydispatcheddoesntwork.nomad.hcl
nomad_tools/entry_gitlab_runner/script.sh
nomad_tools/entry_gitlab_runner/template.jinja.nomad.hcl
nomad_tools/entry_gitlab_runner/waiter.sh
nomad_tools/nomadlib/__init__.py
nomad_tools/nomadlib/_generator.py
nomad_tools/nomadlib/connection.py
nomad_tools/nomadlib/datadict.py
nomad_tools/nomadlib/tools.py
nomad_tools/nomadlib/types.py
nomad_tools-0.5.8.dist-info/licenses/LICENSE
nomad_tools-0.5.8.dist-info/METADATA
nomad_tools-0.5.8.dist-info/WHEEL
nomad_tools-0.5.8.dist-info/entry_points.txt
nomad_tools-0.5.8.dist-info/top_level.txt
nomad_tools-0.5.8.dist-info/RECORD
