Metadata-Version: 2.4
Name: nomad-tools
Version: 0.5.8
Summary: Set of tools and utilities to ease interacting with Hashicorp Nomad scheduling solution.
Author: Kamil Cukrowski
License: GPL-3.0-or-later
Project-URL: homepage, https://github.com/Kamilcuk/nomad-tools
Project-URL: repository, https://github.com/Kamilcuk/nomad-tools
Project-URL: documentation, https://github.com/Kamilcuk/nomad-tools
Requires-Python: >3.7
License-File: LICENSE
Requires-Dist: click==8.1.7
Requires-Dist: python-dateutil>=2.8.2
Requires-Dist: PyYAML>=6.0.1
Requires-Dist: requests>=2.31.0
Requires-Dist: typing_extensions>=4.7.1
Requires-Dist: websocket-client>=1.6.1
Requires-Dist: clickdc>=0.1.0
Requires-Dist: clickforward>=0.0.1
Requires-Dist: python-dotenv>=0.21.1
Requires-Dist: packaging>=16.1
Requires-Dist: requests-toolbelt>=1.0.0
Requires-Dist: jinja2>=3.1.0
Requires-Dist: pydantic<2
Provides-Extra: test
Requires-Dist: pytest==7.4.4; extra == "test"
Requires-Dist: pytest-xdist==3.5.0; extra == "test"
Requires-Dist: pytest-cov==4.1.0; extra == "test"
Dynamic: license-file
